[
  {
    "title": "Account",
    "icon": "mdiAccount",
    "to": "/account/"
  },
  {
    "title": "Organisation",
    "icon": "mdiDomain",
    "to": "/organisation/"
  },
  {
    "title": "Credits",
    "icon": "mdiAlphaCCircle",
    "to": "/credits/"
  },
  {
    "title": "Payment methods",
    "icon": "mdiCreditCard",
    "to": "/paymentmethods/"
  },
  {
    "title": "Subscriptions",
    "icon": "mdiCalendarSync",
    "to": "/subscriptions/"
  },
  {
    "title": "Orders",
    "icon": "mdiCart",
    "to": "/orders/"
  },
  {
    "title": "Invoices",
    "icon": "mdiFileDocumentOutline",
    "to": "/invoices/"
  },
  {
    "title": "API Key",
    "icon": "mdiKeyVariant",
    "to": "/apikey/"
  },
  {
    "title": "Reviews",
    "icon": "mdiStar",
    "to": "/reviews/"
  },
  {
    "title": "Sign out",
    "icon": "mdiLogoutVariant",
    "to": "/signout/",
    "auth": true
  }
]
